{"display_name": "Capy Preset Terrafrost", "name": "Capy Preset Terrafrost.profile", "manifest_version": 9, "flags": ["PRESET"], "dependencies": {"CapyInputs": {"\u27a4 Global Settings": "_", "My Color Scheme is rather Light (settings auto-adjustment; may not yield visible results)": "No", "Highlight Animation For Toggle Handles": "Yes", "Gradient Animation (Toggles & Sliders Only)": "No", "Non-Round Toggles": "No", "Non-Round Sliders": "No", "\u27a4 Toggles": "_", "Toggle Rail 'Enabled'": {"value": "Solid Color", "components": {"Color": "hsla(165, 79.48717948717946%, 61.76470588235294%, 1)", "H-Linear Grad 1": "#ccdb76", "H-Linear Grad 2": "#76dbda", "H-Linear Grad 3": "#db7689", "V-Linear Grad 1": "#eb506f", "V-Linear Grad 2": "#50eb79", "V-Linear Grad 3": "#50baeb"}}, "Toggle Handle 'Enabled'": {"value": "_", "components": {"Color": "hsla(185, 88%, 22%, 1)"}}, "Toggle Rail 'Disabled'": {"value": "_", "components": {"Color": "hsla(324, 12%, 10%, 1)"}}, "Toggle Handle 'Disabled'": {"value": "_", "components": {"Color": "hsla(324, 12%, 19%, 1)"}}, "\u27a4 Sliders": "_", "Slider Fill": {"value": "Solid Color", "components": {"Color": "hsla(169, 69%, 56%, 1)", "Gradient Color 1": "#ccdb76", "Gradient Color 2": "#76dbda", "Gradient Color 3": "#db7689"}}, "Slider Empty": {"value": "_", "components": {"Color": "#ffffff4D"}}, "Slider Handle": {"value": "_", "components": {"Color": "hsla(326, 13%, 35%, 1)"}}, "Slider Highlight": {"value": "_", "components": {"Color": "hsla(0, 0%, 100%, 1)"}}, "\u27a4 Buttons & Dropdowns": "_", "Button Decoration": "Outline", "Button Background": {"value": "Solid Color", "components": {"Color": "hsla(0, 0%, 0%, 0)", "H-Linear Grad 1": "#14af90", "H-Linear Grad 2": "#af1486", "H-Linear Grad 3": "#af4514", "V-Linear Grad 1": "#14af90", "V-Linear Grad 2": "#af1486", "V-Linear Grad 3": "#af4514", "Radial Grad 1": "#14af90", "Radial Grad 2": "#af1486", "Stripes 1": "#14af90", "Stripes 2": "#af1486", "Stripes 3": "#af4514", "Cutoff 1": "#14af90", "Cutoff 2": "#af1486", "Cutoff 3": "#af4514"}}, "Button Foreground": {"value": "_", "components": {"Color": "hsla(333, 12%, 30%, 1)"}}, "Button Highlight Background": {"value": "Solid Color", "components": {"Color": "hsla(0, 0%, 83.92156862745098%, 0)", "H-Linear Grad 1": "#14af90", "H-Linear Grad 2": "#af1486", "H-Linear Grad 3": "#af4514", "V-Linear Grad 1": "#14af90", "V-Linear Grad 2": "#af1486", "V-Linear Grad 3": "#af4514", "Radial Grad 1": "#14af90", "Radial Grad 2": "#af1486", "Stripes 1": "#14af90", "Stripes 2": "#af1486", "Stripes 3": "#af4514", "Cutoff 1": "#14af90", "Cutoff 2": "#af1486", "Cutoff 3": "#af4514"}}, "Button Highlight Foreground": {"value": "_", "components": {"Color": "hsla(0, 0%, 100%, 1)"}}}, "CapyMenu (QAM)": {"\u27a4 Global Settings": "_", "QAM Type": "Inverted Rounded", "Sidebar Layout": "Collapse Top", "Show Sidebar Page Indicator": "No", "Hide Help Page": "Yes", "Extend QAM Styling To Notification Toasts": "Yes", "\u27a4 Content Panel": "_", "Content Panel Background Type": {"value": "Solid Color", "components": {"Solid Color": "hsla(335, 16%, 14%, 1)", "H-Linear Grad 1": "#eb506f", "H-Linear Grad 2": "#50baeb", "V-Linear Grad 1": "#eb506f", "V-Linear Grad 2": "#50eb79", "V-Linear Grad 3": "#50baeb", "Radial Grad 1": "#eb506f", "Radial Grad 2": "#50baeb", "Halo 1": "#eb506f", "Halo 2": "#50eb79", "Halo 3": "#50baeb", "Halo 4": "#dff261", "Halo 5": "#b161f2", "Stripe 1": "#eb506f", "Stripe 2": "#50eb79", "Stripe 3": "#50baeb", "Image Picker": ""}}, "\u21b3 Content Panel Bg Anim (\u274c Solid Color, Stripes, IMG)": "No", "Content Panel Foreground": {"value": "_", "components": {"Color": "hsla(338, 10%, 39%, 1)"}}, "Header Layer 1 Bg Type": {"value": "Solid Colors", "components": {"Color 1": "hsla(338, 14%, 23%, 1)", "Color 2 (Anim Only)": "#eb506f", "Color 3 (Anim Only)": "#50eb79", "Color 4 (Anim Only)": "#50baeb", "H-Linear Grad 1": "#eb506f", "H-Linear Grad 2": "#50eb79", "H-Linear Grad 3": "#50baeb", "V-Linear Grad 1": "#eb506f", "V-Linear Grad 2": "#50baeb", "Halo 1": "#eb506f", "Halo 2": "#50eb79", "Halo 3": "#50baeb", "Halo 4": "#dff261", "Halo 5": "#b161f2", "Stripe 1": "#eb506f", "Stripe 2": "#50eb79", "Stripe 3": "#50baeb", "Cutoff": "#eb506f"}}, "\u21b3 Header Layer 1 Bg Anim (\u274c Stripes, Cutoff)": "No", "Header Layer 2 Bg Type": {"value": "Solid Colors", "components": {"Color 1": "hsla(338, 21%, 17%, 1)", "Color 2 (Anim Only)": "#50eb79", "Color 3 (Anim Only)": "#50baeb", "Color 4 (Anim Only)": "#dff261", "H-Linear Grad 1": "#ccdb76", "H-Linear Grad 2": "#76dbda", "H-Linear Grad 3": "#db7689", "Cutoff": "#50eb79"}}, "\u21b3 Header Layer 2 Bg Anim (\u274c Cutoff)": "No", "Header Foreground": {"value": "_", "components": {"Color": "hsla(320, 14%, 63%, 1)"}}, "\u27a4 Focusable Items In Page": "_", "Focusable Item Bg Highlight Type": {"value": "Solid Colors", "components": {"Color 1": "hsla(168, 54%, 51%, 1)", "Color 2 (Anim Only)": "#50eb79", "Color 3 (Anim Only)": "#50baeb", "Color 4 (Anim Only)": "#dff261", "H-Linear Grad 1": "#eb506f", "H-Linear Grad 2": "#50eb79", "H-Linear Grad 3": "#50baeb", "V-Linear Grad 1": "#eb506f", "V-Linear Grad 2": "#50baeb", "Halo 1": "#f4f4f4", "Halo 2": "#ccc", "Halo 3": "#bab3b3", "Halo 4": "#bfbfbf", "Halo 5": "#8c8c8c", "Stripe 1": "#eb506f", "Stripe 2": "#50eb79", "Stripe 3": "#50baeb"}}, "\u21b3 Focusable Item Highlight Bg Anim (\u274c Stripes)": "No", "Focusable Item Highlight Fg": {"value": "_", "components": {"Color": "hsla(179, 73%, 100%, 1)"}}, "Item Separators": {"value": "_", "components": {"Color": "#00000000"}}, "\u27a4 Sidebar": "_", "Sidebar Panel Background": {"value": "Solid Color", "components": {"Color": "hsla(327, 17%, 12%, 1)", "H-Linear Grad 1": "#eb506f", "H-Linear Grad 2": "#50baeb", "V-Linear Grad 1": "#eb506f", "V-Linear Grad 2": "#50eb79", "V-Linear Grad 3": "#50baeb", "Stripe 1": "hsla(327, 17%, 12%, 1)", "Stripe 2": "hsla(327, 17%, 13%, 1)", "Stripe 3": "hsla(327, 17%, 12%, 1)"}}, "Sidebar Icon": {"value": "_", "components": {"Color": "hsla(339, 61%, 86%, 0.30196078431372547)"}}, "Sidebar Icon Highlight": {"value": "_", "components": {"Color": "hsla(48, 0%, 100%, 0.4)"}}, "Sidebar Icon Bg Highlight": {"value": "Solid Colors", "components": {"Color 1": "hsla(169, 55%, 48%, 1)", "Color 2 (Anim Only)": "#eb506f", "Color 3 (Anim Only)": "#50eb79", "Color 4 (Anim Only)": "#50baeb", "H-Linear Grad 1": "#eb506f", "H-Linear Grad 2": "#50baeb", "V-Linear Grad 1": "#eb506f", "V-Linear Grad 2": "#50eb79", "V-Linear Grad 3": "#50baeb", "Stripe 1": "#eb506f", "Stripe 2": "#50eb79", "Stripe 3": "#50baeb"}}, "\u21b3 Sidebar Icon Highlight Bg Anim (\u274c Stripes)": "No", "Sidebar Page Indicator": {"value": "H-Linear Grad", "components": {"Color 1": "#eb506f", "Color 2 (Anim Only)": "#50eb79", "Color 3 (Anim Only)": "#50baeb", "Color 4 (Anim Only)": "#dff261", "H-Linear Grad 1": "#ccdb76", "H-Linear Grad 2": "#76dbda", "H-Linear Grad 3": "#db7689", "Stripe 1": "#eb506f", "Stripe 2": "#50eb79", "Stripe 3": "#50baeb"}}, "\u21b3 Sidebar Indicator Anim (\u274c Stripes)": "Yes", "\u27a4 Top Bar (Only Visible In-Game)": "_", "Top Bar Background": {"value": "_", "components": {"Color": "hsla(327, 17%, 12%, 1)"}}, "Top Bar Foreground": {"value": "_", "components": {"Color": "hsla(339, 61%, 86%, 0.3)"}}, "Top Bar Bg Highlight": {"value": "_", "components": {"Color": "hsla(340, 55%, 48%, 1)"}}, "Top Bar Fg Highlight": {"value": "_", "components": {"Color": "hsla(0, 0%, 100%, 0.4)"}}, "\u27a4 Other": "_", "Notification Mark": {"value": "_", "components": {"Color": "hsla(57, 36%, 82%, 1)"}}}}}